__init__.py
pycatch_d/__init__.py
pycatch_d/catch.py
pycatch_d/diagnostics.py
pycatch_d-0.0.1.dist-info/LICENSE
pycatch_d-0.0.1.dist-info/METADATA
pycatch_d-0.0.1.dist-info/WHEEL
pycatch_d-0.0.1.dist-info/top_level.txt
pycatch_d-0.0.1.dist-info/RECORD
