Metadata-Version: 2.1
Name: pycatch_d
Version: 0.0.1
Summary: This is a project that automatically identifies the outliers from a given dataset
Author-email: Aseem Anand <aseemanand@gmail.com>, Jagadish Pamarthi <jagadish.vrsec@gmail.com>
Classifier: Programming Language :: Python :: 3
Classifier: License :: OSI Approved :: MIT License
Classifier: Operating System :: OS Independent
Requires-Python: >=3.8
License-File: LICENSE
